cued_speech/__init__.py
cued_speech/cli.py
cued_speech/data_manager.py
cued_speech/decoder.py
cued_speech/decoder_bak.py
cued_speech/decoder_tflite.py
cued_speech/generator.py
cued_speech/data/__init__.py
cued_speech/data/cue_mappings.py
cued_speech/data/download_models.py
cued_speech/data/lexicon.txt
cued_speech/data/phonelist.csv
cued_speech-0.4.2.dist-info/METADATA
cued_speech-0.4.2.dist-info/WHEEL
cued_speech-0.4.2.dist-info/entry_points.txt
cued_speech-0.4.2.dist-info/licenses/LICENSE
cued_speech-0.4.2.dist-info/RECORD
