Metadata-Version: 2.4
Name: cued_speech
Version: 0.4.2
Summary: Cued Speech Processing Tools - Decode and Generate cued speech videos
Project-URL: Homepage, https://github.com/boubacar-sow/cued-speech
Project-URL: Documentation, https://github.com/boubacar-sow/cued-speechblob/main/README.md
Project-URL: Repository, https://github.com/boubacar-sow/cued-speech
Project-URL: Bug Tracker, https://github.com/boubacar-sow/cued-speech/issues
Author-email: Boubacar Sow <boubasow.pro@gmail.com>
Maintainer-email: Boubacar Sow <boubasow.pro@gmail.com>
License-Expression: MIT
License-File: LICENSE
Keywords: accessibility,cued-speech,mediapipe,speech-recognition,video-processing,whisper
Classifier: Development Status :: 4 - Beta
Classifier: Intended Audience :: Developers
Classifier: Intended Audience :: Science/Research
Classifier: License :: OSI Approved :: MIT License
Classifier: Operating System :: OS Independent
Classifier: Programming Language :: Python :: 3
Classifier: Programming Language :: Python :: 3.11
Classifier: Topic :: Multimedia :: Video
Classifier: Topic :: Scientific/Engineering :: Artificial Intelligence
Classifier: Topic :: Software Development :: Libraries :: Python Modules
Requires-Python: <3.12,>=3.11
Requires-Dist: absl-py>=2.3.1
Requires-Dist: click
Requires-Dist: flashlight-text>=0.0.7
Requires-Dist: kenlm>=0.3.0
Requires-Dist: mediapipe>=0.10.14
Requires-Dist: montreal-forced-aligner>=3.2.1
Requires-Dist: moviepy==1.0.3
Requires-Dist: numpy<2.0,>=1.24
Requires-Dist: openai-whisper>=20250625
Requires-Dist: opencv-python<4.12,>=4.8.0
Requires-Dist: pandas<2.1,>=1.5.0
Requires-Dist: praat-textgrids>=1.4.0
Requires-Dist: torch==2.2.2
Requires-Dist: torchaudio==2.2.2
Requires-Dist: torchvision>=0.17.2
Requires-Dist: unicodedata2
Provides-Extra: dev
Requires-Dist: black>=25.1.0; extra == 'dev'
Requires-Dist: flake8>=7.3.0; extra == 'dev'
Requires-Dist: isort>=6.0.1; extra == 'dev'
Requires-Dist: mypy>=1.17.1; extra == 'dev'
Requires-Dist: pytest>=8.4.1; extra == 'dev'
Provides-Extra: docs
Requires-Dist: sphinx; extra == 'docs'
Requires-Dist: sphinx-rtd-theme; extra == 'docs'
